tra_tools/__init__.py
tra_tools/io/__init__.py
tra_tools/io/cmd.py
tra_tools/logger/__init__.py
tra_tools/logger/logger.py
tra_tools/logger/observed.py
tra_tools/logger/sender.py
tra_tools/logger/server.py
tra_tools/logger/tests.py
tra_tools/progress/__init__.py
tra_tools/progress/progress_cmd.py
tra_tools/progress/progress_main.py
tra_tools/progress/progress_mpi.py
tra_tools/progress/progress_notebook.py
tra_tools/scheduler/__init__.py
tra_tools/scheduler/scheduler.py
tra_tools/tracer/__init__.py
tra_tools/tracer/test.py
tra_tools/tracer/tracer.py
tra_tools/zipper/__init__.py
tra_tools/zipper/zipper.py
tra_tools-0.0.9.1.dev0.dist-info/LICENSE
tra_tools-0.0.9.1.dev0.dist-info/METADATA
tra_tools-0.0.9.1.dev0.dist-info/WHEEL
tra_tools-0.0.9.1.dev0.dist-info/top_level.txt
tra_tools-0.0.9.1.dev0.dist-info/RECORD
